Metadata-Version: 2.1
Name: transitions
Version: 0.9.1
Summary: A lightweight, object-oriented Python state machine implementation with many extensions.
Home-page: http://github.com/pytransitions/transitions
Download-URL: https://github.com/pytransitions/transitions/archive/0.9.1.tar.gz
Author: Tal Yarkoni
Author-email: tyarkoni@gmail.com
Maintainer: Alexander Neumann
Maintainer-email: aleneum@gmail.com
License: MIT
Classifier: License :: OSI Approved :: MIT License
Classifier: Programming Language :: Python :: 2
Classifier: Programming Language :: Python :: 2.7
Classifier: Programming Language :: Python :: 3
Classifier: Programming Language :: Python :: 3.8
Classifier: Programming Language :: Python :: 3.9
Classifier: Programming Language :: Python :: 3.10
Classifier: Programming Language :: Python :: 3.11
Classifier: Programming Language :: Python :: 3.12
License-File: LICENSE
Requires-Dist: six
Provides-Extra: diagrams
Requires-Dist: pygraphviz; extra == "diagrams"
Provides-Extra: test
Requires-Dist: pytest; extra == "test"
